message_system/__init__.py
message_system/message_system.py
message_system-0.1.2.dist-info/LICENSE
message_system-0.1.2.dist-info/METADATA
message_system-0.1.2.dist-info/WHEEL
message_system-0.1.2.dist-info/RECORD
