Metadata-Version: 2.1
Name: message-system
Version: 0.1.2
Summary: 
Author: JavierOramas
Author-email: javiale2000@gmail.com
Requires-Python: >=3.10,<4.0
Classifier: Programming Language :: Python :: 3
Classifier: Programming Language :: Python :: 3.10
Classifier: Programming Language :: Python :: 3.11
Requires-Dist: netifaces (>=0.11.0,<0.12.0)
